aad2onnx/__init__.py
aad2onnx/_container.py
aad2onnx/_parse.py
aad2onnx/convert.py
aad2onnx/proto.py
aad2onnx/operator_converters/AadForest.py
aad2onnx/operator_converters/__init__.py
aad2onnx/shape_calculators/AadForest.py
aad2onnx/shape_calculators/__init__.py
aad2onnx-0.1.4.dist-info/LICENSE
aad2onnx-0.1.4.dist-info/METADATA
aad2onnx-0.1.4.dist-info/WHEEL
aad2onnx-0.1.4.dist-info/top_level.txt
aad2onnx-0.1.4.dist-info/RECORD
